{
  "0": {
    "marker_id": 0,
    "num_observations": 44,
    "current": {
      "face": "+Y",
      "corner_permutation": "p0123",
      "corner_reorder": [
        0,
        1,
        2,
        3
      ],
      "rank": 105,
      "score": 1141.7041907877656,
      "num_inliers": 0,
      "mean_dt_mm": 259.68717494305554,
      "mean_dr_deg": 110.20420452544505,
      "mean_reproj_px": 0.19168982057480657
    },
    "best": {
      "face": "+Z",
      "corner_permutation": "r180",
      "corner_reorder": [
        2,
        3,
        0,
        1
      ],
      "num_obs": 44,
      "num_used": 44,
      "num_inliers": 0,
      "mean_dt_mm": 262.33964472835163,
      "mean_dr_deg": 97.49360121148501,
      "mean_reproj_px": 0.3708938968523405,
      "score": 1043.0302422139364
    },
    "top_candidates": [
      {
        "face": "+Z",
        "corner_permutation": "r180",
        "corner_reorder": [
          2,
          3,
          0,
          1
        ],
        "num_obs": 44,
        "num_used": 44,
        "num_inliers": 0,
        "mean_dt_mm": 262.33964472835163,
        "mean_dr_deg": 97.49360121148501,
        "mean_reproj_px": 0.3708938968523405,
        "score": 1043.0302422139364
      },
      {
        "face": "-Z",
        "corner_permutation": "flip_y",
        "corner_reorder": [
          3,
          2,
          1,
          0
        ],
        "num_obs": 44,
        "num_used": 44,
        "num_inliers": 0,
        "mean_dt_mm": 267.32529466284956,
        "mean_dr_deg": 97.59506641977333,
        "mean_reproj_px": 0.37578149064009064,
        "score": 1048.8373890023163
      },
      {
        "face": "-Z",
        "corner_permutation": "r90",
        "corner_reorder": [
          1,
          2,
          3,
          0
        ],
        "num_obs": 44,
        "num_used": 44,
        "num_inliers": 0,
        "mean_dt_mm": 262.2752239874227,
        "mean_dr_deg": 98.76258101978698,
        "mean_reproj_px": 0.2520891317871531,
        "score": 1052.8800504092926
      },
      {
        "face": "+Z",
        "corner_permutation": "flip_anti",
        "corner_reorder": [
          2,
          1,
          0,
          3
        ],
        "num_obs": 44,
        "num_used": 44,
        "num_inliers": 0,
        "mean_dt_mm": 267.80318204383946,
        "mean_dr_deg": 98.72585652142443,
        "mean_reproj_px": 0.24813527884451486,
        "score": 1058.106304772924
      },
      {
        "face": "+Z",
        "corner_permutation": "r270",
        "corner_reorder": [
          3,
          0,
          1,
          2
        ],
        "num_obs": 44,
        "num_used": 44,
        "num_inliers": 0,
        "mean_dt_mm": 263.8875878234006,
        "mean_dr_deg": 100.93690921107874,
        "mean_reproj_px": 0.3387998873357035,
        "score": 1072.0604612867019
      },
      {
        "face": "-Z",
        "corner_permutation": "flip_diag",
        "corner_reorder": [
          0,
          3,
          2,
          1
        ],
        "num_obs": 44,
        "num_used": 44,
        "num_inliers": 0,
        "mean_dt_mm": 265.6202448104272,
        "mean_dr_deg": 100.71589253871758,
        "mean_reproj_px": 0.3789775261859857,
        "score": 1072.1053401725399
      },
      {
        "face": "-Z",
        "corner_permutation": "p0321",
        "corner_reorder": [
          0,
          3,
          2,
          1
        ],
        "num_obs": 44,
        "num_used": 44,
        "num_inliers": 0,
        "mean_dt_mm": 265.6202448104272,
        "mean_dr_deg": 100.71589253871758,
        "mean_reproj_px": 0.3789775261859857,
        "score": 1072.1053401725399
      },
      {
        "face": "-Z",
        "corner_permutation": "r180",
        "corner_reorder": [
          2,
          3,
          0,
          1
        ],
        "num_obs": 44,
        "num_used": 44,
        "num_inliers": 0,
        "mean_dt_mm": 263.49430350349627,
        "mean_dr_deg": 103.50338514223795,
        "mean_reproj_px": 0.2585197231470524,
        "score": 1092.038424087694
      }
    ],
    "score_improvement": 98.6739485738292,
    "examples": [
      {
        "cam_idx": 2,
        "event_id": 9,
        "image_path": "data(1)/data/session/cam2/rgb_00009.jpg",
        "corners": [
          [
            363.0,
            89.0
          ],
          [
            323.0,
            87.0
          ],
          [
            325.0,
            44.0
          ],
          [
            367.0,
            47.0
          ]
        ],
        "visible_ids": [
          0,
          10,
          5,
          21,
          16,
          11,
          6,
          27,
          22,
          32,
          17,
          7,
          12,
          33,
          38,
          28,
          18,
          23,
          8,
          13,
          39,
          34,
          19,
          24,
          9,
          14,
          29,
          30,
          35,
          40,
          20,
          15,
          25,
          41,
          26,
          31,
          36,
          42,
          37
        ],
        "area_px2": 1750.0
      },
      {
        "cam_idx": 2,
        "event_id": 0,
        "image_path": "data(1)/data/session/cam2/rgb_00000.jpg",
        "corners": [
          [
            603.0,
            278.0
          ],
          [
            561.0,
            279.0
          ],
          [
            560.0,
            241.0
          ],
          [
            601.0,
            239.0
          ]
        ],
        "visible_ids": [
          0,
          10,
          21,
          5,
          32,
          16,
          11,
          27,
          38,
          6,
          22,
          33,
          17,
          12,
          28,
          7,
          39,
          23,
          34,
          18,
          29,
          8,
          13,
          40,
          24,
          19,
          35,
          30,
          14,
          41,
          9,
          25,
          36,
          20,
          15,
          31,
          42,
          26,
          37
        ],
        "area_px2": 1600.0
      },
      {
        "cam_idx": 2,
        "event_id": 5,
        "image_path": "data(1)/data/session/cam2/rgb_00005.jpg",
        "corners": [
          [
            258.0,
            67.0
          ],
          [
            222.0,
            41.0
          ],
          [
            236.0,
            7.0
          ],
          [
            270.0,
            33.0
          ]
        ],
        "visible_ids": [
          0,
          4,
          15,
          26,
          9,
          37,
          20,
          31,
          14,
          42,
          25,
          8,
          36,
          19,
          30,
          13,
          41,
          7,
          24,
          35,
          18,
          29,
          12,
          40,
          6,
          23,
          34,
          17,
          28,
          11,
          39,
          5,
          16,
          22,
          33,
          38,
          27,
          10,
          21,
          32
        ],
        "area_px2": 1528.0
      },
      {
        "cam_idx": 2,
        "event_id": 3,
        "image_path": "data(1)/data/session/cam2/rgb_00003.jpg",
        "corners": [
          [
            99.0,
            180.0
          ],
          [
            61.0,
            167.0
          ],
          [
            68.0,
            132.0
          ],
          [
            107.0,
            146.0
          ]
        ],
        "visible_ids": [
          0,
          2,
          38,
          39,
          42,
          41,
          32,
          40,
          37,
          33,
          36,
          35,
          34,
          27,
          28,
          29,
          21,
          31,
          30,
          26,
          25,
          22,
          24,
          23,
          16,
          17,
          10,
          20,
          18,
          15,
          19,
          11,
          12,
          6,
          5,
          9,
          13,
          14,
          8,
          7
        ],
        "area_px2": 1429.5
      },
      {
        "cam_idx": 2,
        "event_id": 17,
        "image_path": "data(1)/data/session/cam2/rgb_00017.jpg",
        "corners": [
          [
            59.0,
            238.0
          ],
          [
            26.0,
            215.0
          ],
          [
            45.0,
            188.0
          ],
          [
            78.0,
            211.0
          ]
        ],
        "visible_ids": [
          31,
          0,
          9,
          8,
          7,
          5,
          6,
          15,
          14,
          12,
          10,
          13,
          11,
          20,
          19,
          18,
          17,
          26,
          16,
          25,
          2,
          24,
          21,
          23,
          22,
          37,
          30,
          29,
          28,
          27,
          36,
          35,
          34,
          32,
          42,
          33,
          41,
          39,
          40,
          38
        ],
        "area_px2": 1328.0
      },
      {
        "cam_idx": 2,
        "event_id": 6,
        "image_path": "data(1)/data/session/cam2/rgb_00006.jpg",
        "corners": [
          [
            87.0,
            98.0
          ],
          [
            56.0,
            88.0
          ],
          [
            70.0,
            54.0
          ],
          [
            101.0,
            64.0
          ]
        ],
        "visible_ids": [
          10,
          5,
          21,
          11,
          16,
          6,
          0,
          32,
          27,
          22,
          7,
          12,
          38,
          17,
          33,
          28,
          23,
          18,
          8,
          13,
          39,
          34,
          29,
          14,
          9,
          19,
          24,
          1,
          40,
          35,
          15,
          20,
          25,
          30,
          41,
          26,
          31,
          36,
          42,
          37
        ],
        "area_px2": 1194.0
      }
    ]
  },
  "1": {
    "marker_id": 1,
    "num_observations": 28,
    "current": {
      "face": "+Z",
      "corner_permutation": "p0231",
      "corner_reorder": [
        0,
        2,
        3,
        1
      ],
      "rank": 14,
      "score": NaN,
      "num_inliers": 0,
      "mean_dt_mm": NaN,
      "mean_dr_deg": NaN,
      "mean_reproj_px": NaN
    },
    "best": {
      "face": "+Z",
      "corner_permutation": "r0",
      "corner_reorder": [
        0,
        1,
        2,
        3
      ],
      "num_obs": 28,
      "num_used": 28,
      "num_inliers": 0,
      "mean_dt_mm": 291.9647797587333,
      "mean_dr_deg": 72.17109792388509,
      "mean_reproj_px": 0.32144342414422494,
      "score": 869.9764499981023
    },
    "top_candidates": [
      {
        "face": "+Z",
        "corner_permutation": "r0",
        "corner_reorder": [
          0,
          1,
          2,
          3
        ],
        "num_obs": 28,
        "num_used": 28,
        "num_inliers": 0,
        "mean_dt_mm": 291.9647797587333,
        "mean_dr_deg": 72.17109792388509,
        "mean_reproj_px": 0.32144342414422494,
        "score": 869.9764499981023
      },
      {
        "face": "+Z",
        "corner_permutation": "p0123",
        "corner_reorder": [
          0,
          1,
          2,
          3
        ],
        "num_obs": 28,
        "num_used": 28,
        "num_inliers": 0,
        "mean_dt_mm": 291.9647797587333,
        "mean_dr_deg": 72.17109792388509,
        "mean_reproj_px": 0.32144342414422494,
        "score": 869.9764499981023
      },
      {
        "face": "+Z",
        "corner_permutation": "r270",
        "corner_reorder": [
          3,
          0,
          1,
          2
        ],
        "num_obs": 28,
        "num_used": 28,
        "num_inliers": 0,
        "mean_dt_mm": 292.225761999438,
        "mean_dr_deg": 78.58473517115597,
        "mean_reproj_px": 0.35562997823701503,
        "score": 921.6149033251598
      },
      {
        "face": "+Z",
        "corner_permutation": "flip_x",
        "corner_reorder": [
          1,
          0,
          3,
          2
        ],
        "num_obs": 28,
        "num_used": 28,
        "num_inliers": 0,
        "mean_dt_mm": 292.83156333016643,
        "mean_dr_deg": 92.04628125508052,
        "mean_reproj_px": 0.30494546245624604,
        "score": 1029.811704295723
      },
      {
        "face": "+Z",
        "corner_permutation": "p1032",
        "corner_reorder": [
          1,
          0,
          3,
          2
        ],
        "num_obs": 28,
        "num_used": 28,
        "num_inliers": 0,
        "mean_dt_mm": 292.83156333016643,
        "mean_dr_deg": 92.04628125508052,
        "mean_reproj_px": 0.30494546245624604,
        "score": 1029.811704295723
      },
      {
        "face": "+Z",
        "corner_permutation": "flip_anti",
        "corner_reorder": [
          2,
          1,
          0,
          3
        ],
        "num_obs": 28,
        "num_used": 28,
        "num_inliers": 0,
        "mean_dt_mm": 292.8474422591075,
        "mean_dr_deg": 95.27600712030674,
        "mean_reproj_px": 0.3070415596326797,
        "score": 1055.6695823408268
      },
      {
        "face": "+Z",
        "corner_permutation": "r90",
        "corner_reorder": [
          1,
          2,
          3,
          0
        ],
        "num_obs": 28,
        "num_used": 28,
        "num_inliers": 0,
        "mean_dt_mm": 289.30677346449727,
        "mean_dr_deg": 124.31603867745905,
        "mean_reproj_px": 0.40786871087982396,
        "score": 1284.6508203059293
      },
      {
        "face": "+Z",
        "corner_permutation": "p1230",
        "corner_reorder": [
          1,
          2,
          3,
          0
        ],
        "num_obs": 28,
        "num_used": 28,
        "num_inliers": 0,
        "mean_dt_mm": 289.30677346449727,
        "mean_dr_deg": 124.31603867745905,
        "mean_reproj_px": 0.40786871087982396,
        "score": 1284.6508203059293
      }
    ],
    "score_improvement": NaN,
    "examples": [
      {
        "cam_idx": 1,
        "event_id": 13,
        "image_path": "data(1)/data/session/cam1/rgb_00013.jpg",
        "corners": [
          [
            581.0,
            428.0
          ],
          [
            626.0,
            431.0
          ],
          [
            620.0,
            470.0
          ],
          [
            575.0,
            468.0
          ]
        ],
        "visible_ids": [
          1,
          0,
          4,
          9,
          5,
          8,
          6,
          7,
          15,
          10,
          14,
          11,
          13,
          12,
          16,
          19,
          26,
          18,
          17,
          21,
          25,
          22,
          23,
          27,
          30,
          37,
          28,
          32,
          42,
          34
        ],
        "area_px2": 1792.5
      },
      {
        "cam_idx": 1,
        "event_id": 15,
        "image_path": "data(1)/data/session/cam1/rgb_00015.jpg",
        "corners": [
          [
            581.0,
            428.0
          ],
          [
            626.0,
            430.0
          ],
          [
            619.0,
            470.0
          ],
          [
            575.0,
            467.0
          ]
        ],
        "visible_ids": [
          1,
          0,
          4,
          9,
          5,
          8,
          6,
          7,
          15,
          10,
          14,
          11,
          12,
          13,
          16,
          18,
          17,
          21,
          26,
          25,
          22,
          23,
          27,
          30,
          37,
          28,
          32,
          36,
          42,
          34
        ],
        "area_px2": 1774.0
      },
      {
        "cam_idx": 1,
        "event_id": 14,
        "image_path": "data(1)/data/session/cam1/rgb_00014.jpg",
        "corners": [
          [
            580.0,
            429.0
          ],
          [
            625.0,
            430.0
          ],
          [
            620.0,
            470.0
          ],
          [
            575.0,
            467.0
          ]
        ],
        "visible_ids": [
          1,
          0,
          4,
          9,
          5,
          8,
          7,
          6,
          15,
          10,
          14,
          11,
          13,
          12,
          16,
          26,
          19,
          21,
          18,
          17,
          25,
          22,
          23,
          27,
          30,
          37,
          28,
          32,
          36,
          42,
          34
        ],
        "area_px2": 1765.0
      },
      {
        "cam_idx": 1,
        "event_id": 11,
        "image_path": "data(1)/data/session/cam1/rgb_00011.jpg",
        "corners": [
          [
            395.0,
            410.0
          ],
          [
            433.0,
            426.0
          ],
          [
            430.0,
            467.0
          ],
          [
            393.0,
            449.0
          ]
        ],
        "visible_ids": [
          1,
          2,
          0,
          9,
          8,
          7,
          6,
          15,
          10,
          14,
          13,
          12,
          16,
          26,
          18,
          17,
          21,
          25,
          22,
          23,
          27,
          30,
          37,
          28,
          32,
          42,
          34
        ],
        "area_px2": 1542.5
      },
      {
        "cam_idx": 1,
        "event_id": 12,
        "image_path": "data(1)/data/session/cam1/rgb_00012.jpg",
        "corners": [
          [
            395.0,
            410.0
          ],
          [
            433.0,
            426.0
          ],
          [
            430.0,
            467.0
          ],
          [
            393.0,
            449.0
          ]
        ],
        "visible_ids": [
          1,
          2,
          0,
          9,
          8,
          7,
          6,
          15,
          10,
          14,
          12,
          13,
          16,
          26,
          19,
          21,
          18,
          17,
          25,
          22,
          23,
          27,
          30,
          37,
          32,
          34,
          42,
          40
        ],
        "area_px2": 1542.5
      },
      {
        "cam_idx": 1,
        "event_id": 9,
        "image_path": "data(1)/data/session/cam1/rgb_00009.jpg",
        "corners": [
          [
            395.0,
            411.0
          ],
          [
            433.0,
            426.0
          ],
          [
            430.0,
            467.0
          ],
          [
            393.0,
            449.0
          ]
        ],
        "visible_ids": [
          1,
          2,
          0,
          9,
          8,
          7,
          6,
          15,
          10,
          14,
          13,
          12,
          16,
          26,
          19,
          17,
          21,
          18,
          25,
          22,
          23,
          27,
          30,
          37,
          28,
          32,
          42,
          34
        ],
        "area_px2": 1522.5
      }
    ]
  },
  "2": {
    "marker_id": 2,
    "num_observations": 34,
    "current": {
      "face": "-X",
      "corner_permutation": "p3210",
      "corner_reorder": [
        3,
        2,
        1,
        0
      ],
      "rank": 139,
      "score": 1393.287969117654,
      "num_inliers": 0,
      "mean_dt_mm": 230.48682802128874,
      "mean_dr_deg": 145.23870632945523,
      "mean_reproj_px": 0.4457452303617065
    },
    "best": {
      "face": "+Z",
      "corner_permutation": "r270",
      "corner_reorder": [
        3,
        0,
        1,
        2
      ],
      "num_obs": 34,
      "num_used": 34,
      "num_inliers": 0,
      "mean_dt_mm": 232.7433109215122,
      "mean_dr_deg": 68.49666636239328,
      "mean_reproj_px": 0.43685633586651607,
      "score": 781.5903544923915
    },
    "top_candidates": [
      {
        "face": "+Z",
        "corner_permutation": "r270",
        "corner_reorder": [
          3,
          0,
          1,
          2
        ],
        "num_obs": 34,
        "num_used": 34,
        "num_inliers": 0,
        "mean_dt_mm": 232.7433109215122,
        "mean_dr_deg": 68.49666636239328,
        "mean_reproj_px": 0.43685633586651607,
        "score": 781.5903544923915
      },
      {
        "face": "-Z",
        "corner_permutation": "flip_diag",
        "corner_reorder": [
          0,
          3,
          2,
          1
        ],
        "num_obs": 34,
        "num_used": 34,
        "num_inliers": 0,
        "mean_dt_mm": 233.79962705527325,
        "mean_dr_deg": 68.49666636239328,
        "mean_reproj_px": 0.43685633586651784,
        "score": 782.6466706261526
      },
      {
        "face": "-Z",
        "corner_permutation": "p0321",
        "corner_reorder": [
          0,
          3,
          2,
          1
        ],
        "num_obs": 34,
        "num_used": 34,
        "num_inliers": 0,
        "mean_dt_mm": 233.79962705527325,
        "mean_dr_deg": 68.49666636239328,
        "mean_reproj_px": 0.43685633586651784,
        "score": 782.6466706261526
      },
      {
        "face": "-Z",
        "corner_permutation": "flip_x",
        "corner_reorder": [
          1,
          0,
          3,
          2
        ],
        "num_obs": 34,
        "num_used": 34,
        "num_inliers": 0,
        "mean_dt_mm": 233.66813100509603,
        "mean_dr_deg": 75.50786710067068,
        "mean_reproj_px": 0.3980161009197236,
        "score": 838.5271000123009
      },
      {
        "face": "-Z",
        "corner_permutation": "p1032",
        "corner_reorder": [
          1,
          0,
          3,
          2
        ],
        "num_obs": 34,
        "num_used": 34,
        "num_inliers": 0,
        "mean_dt_mm": 233.66813100509603,
        "mean_dr_deg": 75.50786710067068,
        "mean_reproj_px": 0.3980161009197236,
        "score": 838.5271000123009
      },
      {
        "face": "+Z",
        "corner_permutation": "r0",
        "corner_reorder": [
          0,
          1,
          2,
          3
        ],
        "num_obs": 34,
        "num_used": 34,
        "num_inliers": 0,
        "mean_dt_mm": 231.15548729940838,
        "mean_dr_deg": 75.99402059978927,
        "mean_reproj_px": 0.297681398405613,
        "score": 839.7030148945337
      },
      {
        "face": "+Z",
        "corner_permutation": "p0123",
        "corner_reorder": [
          0,
          1,
          2,
          3
        ],
        "num_obs": 34,
        "num_used": 34,
        "num_inliers": 0,
        "mean_dt_mm": 231.15548729940838,
        "mean_dr_deg": 75.99402059978927,
        "mean_reproj_px": 0.297681398405613,
        "score": 839.7030148945337
      },
      {
        "face": "-Z",
        "corner_permutation": "r90",
        "corner_reorder": [
          1,
          2,
          3,
          0
        ],
        "num_obs": 34,
        "num_used": 34,
        "num_inliers": 0,
        "mean_dt_mm": 229.3738329432947,
        "mean_dr_deg": 91.56385839975248,
        "mean_reproj_px": 0.24988492229717368,
        "score": 962.3844699859088
      }
    ],
    "score_improvement": 611.6976146252625,
    "examples": [
      {
        "cam_idx": 3,
        "event_id": 13,
        "image_path": "data(1)/data/session/cam3/rgb_00013.jpg",
        "corners": [
          [
            137.0,
            296.0
          ],
          [
            165.0,
            299.0
          ],
          [
            166.0,
            332.0
          ],
          [
            139.0,
            328.0
          ]
        ],
        "visible_ids": [
          2,
          3,
          0,
          32,
          21,
          10
        ],
        "area_px2": 888.5
      },
      {
        "cam_idx": 3,
        "event_id": 14,
        "image_path": "data(1)/data/session/cam3/rgb_00014.jpg",
        "corners": [
          [
            137.0,
            296.0
          ],
          [
            165.0,
            299.0
          ],
          [
            166.0,
            332.0
          ],
          [
            139.0,
            328.0
          ]
        ],
        "visible_ids": [
          2,
          3,
          0,
          32,
          21,
          38,
          10,
          5,
          34
        ],
        "area_px2": 888.5
      },
      {
        "cam_idx": 3,
        "event_id": 15,
        "image_path": "data(1)/data/session/cam3/rgb_00015.jpg",
        "corners": [
          [
            137.0,
            296.0
          ],
          [
            165.0,
            299.0
          ],
          [
            166.0,
            332.0
          ],
          [
            139.0,
            328.0
          ]
        ],
        "visible_ids": [
          2,
          3,
          0,
          32,
          38,
          21,
          10,
          5,
          34
        ],
        "area_px2": 888.5
      },
      {
        "cam_idx": 1,
        "event_id": 16,
        "image_path": "data(1)/data/session/cam1/rgb_00016.jpg",
        "corners": [
          [
            504.0,
            327.0
          ],
          [
            533.0,
            335.0
          ],
          [
            530.0,
            364.0
          ],
          [
            501.0,
            354.0
          ]
        ],
        "visible_ids": [
          2,
          9,
          3,
          5,
          0,
          8,
          6,
          7,
          15,
          10,
          14,
          11,
          13,
          12,
          16,
          19,
          17,
          26,
          21,
          18,
          25,
          22,
          23,
          27,
          30,
          37,
          28,
          32,
          33,
          34,
          42
        ],
        "area_px2": 839.0
      },
      {
        "cam_idx": 1,
        "event_id": 17,
        "image_path": "data(1)/data/session/cam1/rgb_00017.jpg",
        "corners": [
          [
            504.0,
            327.0
          ],
          [
            533.0,
            335.0
          ],
          [
            530.0,
            364.0
          ],
          [
            501.0,
            354.0
          ]
        ],
        "visible_ids": [
          2,
          9,
          5,
          0,
          8,
          3,
          7,
          6,
          15,
          10,
          14,
          11,
          12,
          13,
          16,
          19,
          21,
          18,
          17,
          26,
          25,
          22,
          23,
          27,
          30,
          37,
          32,
          33,
          42,
          34
        ],
        "area_px2": 839.0
      },
      {
        "cam_idx": 0,
        "event_id": 3,
        "image_path": "data(1)/data/session/cam0/rgb_00003.jpg",
        "corners": [
          [
            218.0,
            372.0
          ],
          [
            234.0,
            389.0
          ],
          [
            233.0,
            441.0
          ],
          [
            218.0,
            421.0
          ]
        ],
        "visible_ids": [
          3,
          2,
          0,
          37,
          31,
          26,
          40,
          30,
          35,
          25,
          29,
          9
        ],
        "area_px2": 792.0
      }
    ]
  },
  "3": {
    "marker_id": 3,
    "num_observations": 29,
    "current": {
      "face": "-Z",
      "corner_permutation": "p2013",
      "corner_reorder": [
        2,
        0,
        1,
        3
      ],
      "rank": 53,
      "score": NaN,
      "num_inliers": 0,
      "mean_dt_mm": NaN,
      "mean_dr_deg": NaN,
      "mean_reproj_px": NaN
    },
    "best": {
      "face": "+Z",
      "corner_permutation": "r270",
      "corner_reorder": [
        3,
        0,
        1,
        2
      ],
      "num_obs": 29,
      "num_used": 29,
      "num_inliers": 0,
      "mean_dt_mm": 241.90309516244076,
      "mean_dr_deg": 50.57423337696866,
      "mean_reproj_px": 0.18777013224251396,
      "score": 646.872502442675
    },
    "top_candidates": [
      {
        "face": "+Z",
        "corner_permutation": "r270",
        "corner_reorder": [
          3,
          0,
          1,
          2
        ],
        "num_obs": 29,
        "num_used": 29,
        "num_inliers": 0,
        "mean_dt_mm": 241.90309516244076,
        "mean_dr_deg": 50.57423337696866,
        "mean_reproj_px": 0.18777013224251396,
        "score": 646.872502442675
      },
      {
        "face": "-Z",
        "corner_permutation": "flip_diag",
        "corner_reorder": [
          0,
          3,
          2,
          1
        ],
        "num_obs": 29,
        "num_used": 29,
        "num_inliers": 0,
        "mean_dt_mm": 248.5004069152962,
        "mean_dr_deg": 50.57423337696867,
        "mean_reproj_px": 0.18777013224251773,
        "score": 653.4698141955306
      },
      {
        "face": "-Z",
        "corner_permutation": "p0321",
        "corner_reorder": [
          0,
          3,
          2,
          1
        ],
        "num_obs": 29,
        "num_used": 29,
        "num_inliers": 0,
        "mean_dt_mm": 248.5004069152962,
        "mean_dr_deg": 50.57423337696867,
        "mean_reproj_px": 0.18777013224251773,
        "score": 653.4698141955306
      },
      {
        "face": "+Z",
        "corner_permutation": "r0",
        "corner_reorder": [
          0,
          1,
          2,
          3
        ],
        "num_obs": 29,
        "num_used": 29,
        "num_inliers": 0,
        "mean_dt_mm": 241.5365496527607,
        "mean_dr_deg": 54.234270806046794,
        "mean_reproj_px": 0.18862538671138626,
        "score": 675.7879668745578
      },
      {
        "face": "+Z",
        "corner_permutation": "p0123",
        "corner_reorder": [
          0,
          1,
          2,
          3
        ],
        "num_obs": 29,
        "num_used": 29,
        "num_inliers": 0,
        "mean_dt_mm": 241.5365496527607,
        "mean_dr_deg": 54.234270806046794,
        "mean_reproj_px": 0.18862538671138626,
        "score": 675.7879668745578
      },
      {
        "face": "-Z",
        "corner_permutation": "flip_x",
        "corner_reorder": [
          1,
          0,
          3,
          2
        ],
        "num_obs": 29,
        "num_used": 29,
        "num_inliers": 0,
        "mean_dt_mm": 248.85045312911552,
        "mean_dr_deg": 54.234270806046794,
        "mean_reproj_px": 0.18862538671138385,
        "score": 683.1018703509127
      },
      {
        "face": "-Z",
        "corner_permutation": "p1032",
        "corner_reorder": [
          1,
          0,
          3,
          2
        ],
        "num_obs": 29,
        "num_used": 29,
        "num_inliers": 0,
        "mean_dt_mm": 248.85045312911552,
        "mean_dr_deg": 54.234270806046794,
        "mean_reproj_px": 0.18862538671138385,
        "score": 683.1018703509127
      },
      {
        "face": "-Z",
        "corner_permutation": "r90",
        "corner_reorder": [
          1,
          2,
          3,
          0
        ],
        "num_obs": 29,
        "num_used": 29,
        "num_inliers": 0,
        "mean_dt_mm": 239.48826289838073,
        "mean_dr_deg": 108.64830884896027,
        "mean_reproj_px": 0.25985647502977954,
        "score": 1109.1944466401224
      }
    ],
    "score_improvement": NaN,
    "examples": [
      {
        "cam_idx": 0,
        "event_id": 3,
        "image_path": "data(1)/data/session/cam0/rgb_00003.jpg",
        "corners": [
          [
            248.0,
            391.0
          ],
          [
            298.0,
            384.0
          ],
          [
            297.0,
            434.0
          ],
          [
            247.0,
            444.0
          ]
        ],
        "visible_ids": [
          3,
          2,
          0,
          37,
          31,
          26,
          40,
          30,
          35,
          25,
          29,
          9
        ],
        "area_px2": 2566.5
      },
      {
        "cam_idx": 0,
        "event_id": 4,
        "image_path": "data(1)/data/session/cam0/rgb_00004.jpg",
        "corners": [
          [
            248.0,
            391.0
          ],
          [
            298.0,
            384.0
          ],
          [
            297.0,
            434.0
          ],
          [
            247.0,
            444.0
          ]
        ],
        "visible_ids": [
          3,
          2,
          0,
          37,
          26,
          35,
          30,
          25,
          20
        ],
        "area_px2": 2566.5
      },
      {
        "cam_idx": 0,
        "event_id": 5,
        "image_path": "data(1)/data/session/cam0/rgb_00005.jpg",
        "corners": [
          [
            248.0,
            391.0
          ],
          [
            298.0,
            384.0
          ],
          [
            297.0,
            434.0
          ],
          [
            247.0,
            444.0
          ]
        ],
        "visible_ids": [
          3,
          2,
          0,
          37,
          31,
          26,
          40,
          30,
          35,
          25,
          29
        ],
        "area_px2": 2566.5
      },
      {
        "cam_idx": 0,
        "event_id": 6,
        "image_path": "data(1)/data/session/cam0/rgb_00006.jpg",
        "corners": [
          [
            248.0,
            391.0
          ],
          [
            298.0,
            384.0
          ],
          [
            297.0,
            434.0
          ],
          [
            247.0,
            444.0
          ]
        ],
        "visible_ids": [
          3,
          2,
          0,
          37,
          31,
          26,
          40,
          30,
          35,
          20,
          25,
          13,
          12
        ],
        "area_px2": 2566.5
      },
      {
        "cam_idx": 0,
        "event_id": 7,
        "image_path": "data(1)/data/session/cam0/rgb_00007.jpg",
        "corners": [
          [
            462.0,
            294.0
          ],
          [
            488.0,
            294.0
          ],
          [
            486.0,
            322.0
          ],
          [
            460.0,
            322.0
          ]
        ],
        "visible_ids": [
          3,
          42,
          37,
          41,
          31,
          36,
          26,
          2,
          40,
          35,
          30,
          25
        ],
        "area_px2": 728.0
      },
      {
        "cam_idx": 0,
        "event_id": 8,
        "image_path": "data(1)/data/session/cam0/rgb_00008.jpg",
        "corners": [
          [
            462.0,
            294.0
          ],
          [
            488.0,
            294.0
          ],
          [
            486.0,
            322.0
          ],
          [
            460.0,
            322.0
          ]
        ],
        "visible_ids": [
          3,
          42,
          37,
          41,
          31,
          36,
          26,
          2,
          35,
          30,
          40,
          25
        ],
        "area_px2": 728.0
      }
    ]
  },
  "4": {
    "marker_id": 4,
    "num_observations": 28,
    "current": {
      "face": "+X",
      "corner_permutation": "p1032",
      "corner_reorder": [
        1,
        0,
        3,
        2
      ],
      "rank": 10,
      "score": 892.7054129329364,
      "num_inliers": 0,
      "mean_dt_mm": 309.63307027007244,
      "mean_dr_deg": 72.80063736411941,
      "mean_reproj_px": 0.3336218749542847
    },
    "best": {
      "face": "+Z",
      "corner_permutation": "r0",
      "corner_reorder": [
        0,
        1,
        2,
        3
      ],
      "num_obs": 28,
      "num_used": 28,
      "num_inliers": 0,
      "mean_dt_mm": 305.96936895808665,
      "mean_dr_deg": 64.53538261173648,
      "mean_reproj_px": 0.29754753965692915,
      "score": 822.8475249312924
    },
    "top_candidates": [
      {
        "face": "+Z",
        "corner_permutation": "r0",
        "corner_reorder": [
          0,
          1,
          2,
          3
        ],
        "num_obs": 28,
        "num_used": 28,
        "num_inliers": 0,
        "mean_dt_mm": 305.96936895808665,
        "mean_dr_deg": 64.53538261173648,
        "mean_reproj_px": 0.29754753965692915,
        "score": 822.8475249312924
      },
      {
        "face": "+Z",
        "corner_permutation": "p0123",
        "corner_reorder": [
          0,
          1,
          2,
          3
        ],
        "num_obs": 28,
        "num_used": 28,
        "num_inliers": 0,
        "mean_dt_mm": 305.96936895808665,
        "mean_dr_deg": 64.53538261173648,
        "mean_reproj_px": 0.29754753965692915,
        "score": 822.8475249312924
      },
      {
        "face": "+Z",
        "corner_permutation": "r270",
        "corner_reorder": [
          3,
          0,
          1,
          2
        ],
        "num_obs": 28,
        "num_used": 28,
        "num_inliers": 0,
        "mean_dt_mm": 307.85268894289317,
        "mean_dr_deg": 64.67631909152128,
        "mean_reproj_px": 0.26987770416487455,
        "score": 825.8029970833932
      },
      {
        "face": "+Z",
        "corner_permutation": "p3012",
        "corner_reorder": [
          3,
          0,
          1,
          2
        ],
        "num_obs": 28,
        "num_used": 28,
        "num_inliers": 0,
        "mean_dt_mm": 307.85268894289317,
        "mean_dr_deg": 64.67631909152128,
        "mean_reproj_px": 0.26987770416487455,
        "score": 825.8029970833932
      },
      {
        "face": "-Z",
        "corner_permutation": "flip_diag",
        "corner_reorder": [
          0,
          3,
          2,
          1
        ],
        "num_obs": 28,
        "num_used": 28,
        "num_inliers": 0,
        "mean_dt_mm": 313.153306835725,
        "mean_dr_deg": 64.67631909152128,
        "mean_reproj_px": 0.26987770416487583,
        "score": 831.1036149762249
      },
      {
        "face": "-Z",
        "corner_permutation": "p0321",
        "corner_reorder": [
          0,
          3,
          2,
          1
        ],
        "num_obs": 28,
        "num_used": 28,
        "num_inliers": 0,
        "mean_dt_mm": 313.153306835725,
        "mean_dr_deg": 64.67631909152128,
        "mean_reproj_px": 0.26987770416487583,
        "score": 831.1036149762249
      },
      {
        "face": "-Z",
        "corner_permutation": "flip_x",
        "corner_reorder": [
          1,
          0,
          3,
          2
        ],
        "num_obs": 28,
        "num_used": 28,
        "num_inliers": 0,
        "mean_dt_mm": 314.9680476706008,
        "mean_dr_deg": 64.53538261173654,
        "mean_reproj_px": 0.2975475396569351,
        "score": 831.8462036438069
      },
      {
        "face": "-Z",
        "corner_permutation": "p1032",
        "corner_reorder": [
          1,
          0,
          3,
          2
        ],
        "num_obs": 28,
        "num_used": 28,
        "num_inliers": 0,
        "mean_dt_mm": 314.9680476706008,
        "mean_dr_deg": 64.53538261173654,
        "mean_reproj_px": 0.2975475396569351,
        "score": 831.8462036438069
      }
    ],
    "score_improvement": 69.85788800164403,
    "examples": [
      {
        "cam_idx": 3,
        "event_id": 16,
        "image_path": "data(1)/data/session/cam3/rgb_00016.jpg",
        "corners": [
          [
            346.0,
            325.0
          ],
          [
            379.0,
            319.0
          ],
          [
            379.0,
            355.0
          ],
          [
            346.0,
            362.0
          ]
        ],
        "visible_ids": [
          4,
          3,
          0,
          32,
          38,
          5,
          34
        ],
        "area_px2": 1204.5
      },
      {
        "cam_idx": 3,
        "event_id": 17,
        "image_path": "data(1)/data/session/cam3/rgb_00017.jpg",
        "corners": [
          [
            346.0,
            325.0
          ],
          [
            379.0,
            319.0
          ],
          [
            379.0,
            355.0
          ],
          [
            346.0,
            362.0
          ]
        ],
        "visible_ids": [
          4,
          3,
          0,
          32,
          10,
          5,
          34
        ],
        "area_px2": 1204.5
      },
      {
        "cam_idx": 1,
        "event_id": 7,
        "image_path": "data(1)/data/session/cam1/rgb_00007.jpg",
        "corners": [
          [
            52.0,
            395.0
          ],
          [
            79.0,
            407.0
          ],
          [
            81.0,
            446.0
          ],
          [
            56.0,
            433.0
          ]
        ],
        "visible_ids": [
          1,
          4,
          0,
          5,
          8,
          6,
          7,
          10,
          14,
          11,
          13,
          12,
          16,
          19,
          18,
          17,
          26,
          21,
          25,
          22,
          23,
          27,
          30,
          37,
          28,
          33,
          42,
          34
        ],
        "area_px2": 963.5
      },
      {
        "cam_idx": 2,
        "event_id": 5,
        "image_path": "data(1)/data/session/cam2/rgb_00005.jpg",
        "corners": [
          [
            216.0,
            52.0
          ],
          [
            251.0,
            77.0
          ],
          [
            229.0,
            89.0
          ],
          [
            195.0,
            65.0
          ]
        ],
        "visible_ids": [
          0,
          4,
          15,
          26,
          9,
          37,
          20,
          31,
          14,
          42,
          25,
          8,
          36,
          19,
          30,
          13,
          41,
          7,
          24,
          35,
          18,
          29,
          12,
          40,
          6,
          23,
          34,
          17,
          28,
          11,
          39,
          5,
          16,
          22,
          33,
          38,
          27,
          10,
          21,
          32
        ],
        "area_px2": 958.0
      },
      {
        "cam_idx": 1,
        "event_id": 8,
        "image_path": "data(1)/data/session/cam1/rgb_00008.jpg",
        "corners": [
          [
            53.0,
            395.0
          ],
          [
            79.0,
            407.0
          ],
          [
            82.0,
            445.0
          ],
          [
            56.0,
            433.0
          ]
        ],
        "visible_ids": [
          1,
          4,
          0,
          5,
          8,
          7,
          6,
          10,
          14,
          11,
          13,
          12,
          16,
          19,
          18,
          17,
          26,
          21,
          25,
          22,
          23,
          27,
          30,
          37,
          28,
          32,
          33,
          42,
          34
        ],
        "area_px2": 952.0
      },
      {
        "cam_idx": 1,
        "event_id": 0,
        "image_path": "data(1)/data/session/cam1/rgb_00000.jpg",
        "corners": [
          [
            500.0,
            321.0
          ],
          [
            530.0,
            323.0
          ],
          [
            527.0,
            350.0
          ],
          [
            497.0,
            348.0
          ]
        ],
        "visible_ids": [
          4,
          9,
          5,
          8,
          3,
          6,
          15,
          7,
          10,
          0,
          11,
          13,
          12,
          16,
          19,
          21,
          26,
          17,
          18,
          25,
          22,
          23,
          24,
          27,
          37,
          30,
          28,
          34,
          42
        ],
        "area_px2": 816.0
      }
    ]
  }
}